bibtools/formatters.py
bibtools/json2bibtex.py
bibtools/pubmed.py
bibtools/scihub.py
bibtools/utils.py
bibtools_pkg-0.1.16.data/scripts/bibtools
bibtools_pkg-0.1.16.dist-info/LICENSE
bibtools_pkg-0.1.16.dist-info/METADATA
bibtools_pkg-0.1.16.dist-info/WHEEL
bibtools_pkg-0.1.16.dist-info/top_level.txt
bibtools_pkg-0.1.16.dist-info/RECORD
