Metadata-Version: 2.1
Name: bibtools-pkg
Version: 0.1.16
Summary: Utils for pubmed, scihub and bibtex
Home-page: https://github.com/synthaze/bibtools
Author: Florian Malard, PhD
Author-email: florian.malard@gmail.com
License: UNKNOWN
Project-URL: Bug Tracker, https://github.com/synthaze/bibtools/issues
Platform: UNKNOWN
Classifier: Programming Language :: Python :: 3
Classifier: License :: OSI Approved :: GNU General Public License v3 (GPLv3)
Classifier: Operating System :: OS Independent
Requires-Python: >=3.7
License-File: LICENSE
Requires-Dist: requests (==2.25.1)
Requires-Dist: pybasics (==0.3.2)
Requires-Dist: utilsovs-pkg (==0.9.5)
